pdpipewrench/__init__.py
pdpipewrench/exceptions.py
pdpipewrench/pdpipewrench.py
pdpipewrench-0.2.0.dist-info/LICENSE
pdpipewrench-0.2.0.dist-info/METADATA
pdpipewrench-0.2.0.dist-info/WHEEL
pdpipewrench-0.2.0.dist-info/top_level.txt
pdpipewrench-0.2.0.dist-info/RECORD
