Metadata-Version: 2.1
Name: pdpipewrench
Version: 0.2.0
Summary: YAML-configurable Pandas pipelines.
Home-page: https://github.com/blakeNaccarato/pdpipewrench
Author: Blake Naccarato
License: UNKNOWN
Platform: UNKNOWN
Requires-Python: >=3.7
Requires-Dist: pandas
Requires-Dist: pdpipe
Requires-Dist: engarde
Requires-Dist: confuse
Provides-Extra: dev
Requires-Dist: setuptools ; extra == 'dev'
Requires-Dist: wheel ; extra == 'dev'
Requires-Dist: twine ; extra == 'dev'
Requires-Dist: numpy ; extra == 'dev'
Requires-Dist: scipy ; extra == 'dev'
Requires-Dist: dtale ; extra == 'dev'
Requires-Dist: doc8 ; extra == 'dev'
Requires-Dist: jupyter ; extra == 'dev'
Requires-Dist: black ; extra == 'dev'
Requires-Dist: flake8 ; extra == 'dev'
Requires-Dist: mypy ; extra == 'dev'
Requires-Dist: pylint ; extra == 'dev'
Requires-Dist: matplotlib ; extra == 'dev'
Requires-Dist: PyQt5 ; extra == 'dev'
Requires-Dist: rope ; extra == 'dev'
